odoo/addons/helpdesk_mgmt_project_domain/README.rst
odoo/addons/helpdesk_mgmt_project_domain/__init__.py
odoo/addons/helpdesk_mgmt_project_domain/__manifest__.py
odoo/addons/helpdesk_mgmt_project_domain/demo/helpdesk_mgmt_project_domain_demo.xml
odoo/addons/helpdesk_mgmt_project_domain/i18n/helpdesk_mgmt_project_domain.pot
odoo/addons/helpdesk_mgmt_project_domain/i18n/it.po
odoo/addons/helpdesk_mgmt_project_domain/models/__init__.py
odoo/addons/helpdesk_mgmt_project_domain/models/helpdesk_ticket.py
odoo/addons/helpdesk_mgmt_project_domain/models/helpdesk_ticket_team.py
odoo/addons/helpdesk_mgmt_project_domain/models/res_company.py
odoo/addons/helpdesk_mgmt_project_domain/models/res_config_settings.py
odoo/addons/helpdesk_mgmt_project_domain/readme/CONFIGURE.md
odoo/addons/helpdesk_mgmt_project_domain/readme/CONTEXT.md
odoo/addons/helpdesk_mgmt_project_domain/readme/CONTRIBUTORS.md
odoo/addons/helpdesk_mgmt_project_domain/readme/DESCRIPTION.md
odoo/addons/helpdesk_mgmt_project_domain/readme/USAGE.md
odoo/addons/helpdesk_mgmt_project_domain/static/description/icon.png
odoo/addons/helpdesk_mgmt_project_domain/static/description/index.html
odoo/addons/helpdesk_mgmt_project_domain/tests/__init__.py
odoo/addons/helpdesk_mgmt_project_domain/tests/test_helpdesk_ticket.py
odoo/addons/helpdesk_mgmt_project_domain/tests/test_helpdesk_ticket_team.py
odoo/addons/helpdesk_mgmt_project_domain/views/helpdesk_ticket_team_view.xml
odoo/addons/helpdesk_mgmt_project_domain/views/helpdesk_ticket_view.xml
odoo/addons/helpdesk_mgmt_project_domain/views/res_config_settings.xml
odoo_addon_helpdesk_mgmt_project_domain-17.0.1.0.0.2.dist-info/METADATA
odoo_addon_helpdesk_mgmt_project_domain-17.0.1.0.0.2.dist-info/WHEEL
odoo_addon_helpdesk_mgmt_project_domain-17.0.1.0.0.2.dist-info/top_level.txt
odoo_addon_helpdesk_mgmt_project_domain-17.0.1.0.0.2.dist-info/RECORD
